boonli_api/__init__.py
boonli_api/api.py
boonli_api/py.typed
boonli_api/utils.py
boonli_api-0.1.4.dist-info/LICENSE
boonli_api-0.1.4.dist-info/WHEEL
boonli_api-0.1.4.dist-info/METADATA
boonli_api-0.1.4.dist-info/RECORD
