Metadata-Version: 2.1
Name: boonli-api
Version: 0.1.4
Summary: API allowing you to fecth menus from boonli.com
Home-page: https://github.com/beaufour/boonli_api
License: Apache-2.0
Author: Allan Beaufour
Author-email: allan@beaufour.dk
Requires-Python: >=3.7,<4.0
Classifier: License :: OSI Approved :: Apache Software License
Classifier: Programming Language :: Python :: 3
Classifier: Programming Language :: Python :: 3.7
Classifier: Programming Language :: Python :: 3.8
Classifier: Programming Language :: Python :: 3.9
Classifier: Programming Language :: Python :: 3.10
Classifier: Programming Language :: Python :: 3.11
Requires-Dist: bs4 (>=0.0.1,<0.0.2)
Requires-Dist: icalendar (>=4.1.0,<5.0.0)
Requires-Dist: lxml (>=4.9.1,<5.0.0)
Requires-Dist: python-dateutil (>=2.8.2,<3.0.0)
Requires-Dist: requests (>=2.28.1,<3.0.0)
Requires-Dist: requests-toolbelt (>=0.9.1,<0.10.0)
Requires-Dist: typing-extensions (>=4.3.0,<4.4.0) ; python_version < "3.8"
Project-URL: Repository, https://github.com/beaufour/boonli_api
